odoo10_addon_account_payment_line_cancel-10.0.1.0.0.99.dev4-py2.7-nspkg.pth
odoo/addons/account_payment_line_cancel/README.rst
odoo/addons/account_payment_line_cancel/__init__.py
odoo/addons/account_payment_line_cancel/__manifest__.py
odoo/addons/account_payment_line_cancel/i18n/account_payment_line_cancel.pot
odoo/addons/account_payment_line_cancel/i18n/pt.po
odoo/addons/account_payment_line_cancel/models/__init__.py
odoo/addons/account_payment_line_cancel/models/account_payment_line.py
odoo/addons/account_payment_line_cancel/models/invoice.py
odoo/addons/account_payment_line_cancel/static/description/icon.png
odoo/addons/account_payment_line_cancel/tests/__init__.py
odoo/addons/account_payment_line_cancel/tests/test_payment_cancel.py
odoo/addons/account_payment_line_cancel/views/invoice_view.xml
odoo/addons/account_payment_line_cancel/views/payment_line_view.xml
odoo/addons/account_payment_line_cancel/wizards/__init__.py
odoo/addons/account_payment_line_cancel/wizards/invoice_free_wizard.py
odoo10_addon_account_payment_line_cancel-10.0.1.0.0.99.dev4.dist-info/METADATA
odoo10_addon_account_payment_line_cancel-10.0.1.0.0.99.dev4.dist-info/RECORD
odoo10_addon_account_payment_line_cancel-10.0.1.0.0.99.dev4.dist-info/WHEEL
odoo10_addon_account_payment_line_cancel-10.0.1.0.0.99.dev4.dist-info/namespace_packages.txt
odoo10_addon_account_payment_line_cancel-10.0.1.0.0.99.dev4.dist-info/top_level.txt
